cloudflareddns/__about__.py
cloudflareddns/__init__.py
cloudflareddns/__main__.py
cloudflareddns/cloudflareddns.py
cloudflareddns-0.0.8.dist-info/LICENSE
cloudflareddns-0.0.8.dist-info/METADATA
cloudflareddns-0.0.8.dist-info/WHEEL
cloudflareddns-0.0.8.dist-info/entry_points.txt
cloudflareddns-0.0.8.dist-info/top_level.txt
cloudflareddns-0.0.8.dist-info/RECORD
