Metadata-Version: 2.1
Name: cloudflareddns
Version: 0.0.8
Summary: A CLI tool to use Cloudflare as a DDNS provider
Home-page: https://github.com/dvershinin/cloudflareddns
Author: Danila Vershinin
Author-email: info@getpagespeed.com
License: BSD
Platform: UNKNOWN
Classifier: Intended Audience :: Developers
Classifier: Intended Audience :: System Administrators
Classifier: Operating System :: OS Independent
Classifier: Topic :: Software Development
Requires-Dist: requests
Requires-Dist: tldextract
Requires-Dist: cloudflare (>=2.3.1)
Provides-Extra: tests
Requires-Dist: requests ; extra == 'tests'
Requires-Dist: tldextract ; extra == 'tests'
Requires-Dist: cloudflare (>=2.3.1) ; extra == 'tests'
Requires-Dist: pytest ; extra == 'tests'
Requires-Dist: flake8 ; extra == 'tests'
Requires-Dist: faker ; extra == 'tests'
